padasip/__init__.py
padasip/ann/__init__.py
padasip/ann/mlp.py
padasip/detection/__init__.py
padasip/detection/elbnd.py
padasip/detection/ese.py
padasip/detection/le.py
padasip/filters/__init__.py
padasip/filters/ap.py
padasip/filters/base_filter.py
padasip/filters/gmcc.py
padasip/filters/gngd.py
padasip/filters/llncosh.py
padasip/filters/lmf.py
padasip/filters/lms.py
padasip/filters/nlmf.py
padasip/filters/nlms.py
padasip/filters/nsslms.py
padasip/filters/ocnlms.py
padasip/filters/rls.py
padasip/filters/sslms.py
padasip/misc/__init__.py
padasip/misc/error_evaluation.py
padasip/preprocess/__init__.py
padasip/preprocess/input_from_history.py
padasip/preprocess/lda.py
padasip/preprocess/pca.py
padasip/preprocess/standardize.py
padasip/preprocess/standardize_back.py
padasip-1.2.1.dist-info/LICENSE.txt
padasip-1.2.1.dist-info/METADATA
padasip-1.2.1.dist-info/WHEEL
padasip-1.2.1.dist-info/top_level.txt
padasip-1.2.1.dist-info/RECORD
