Metadata-Version: 2.1
Name: padasip
Version: 1.2.1
Summary: Python Adaptive Signal Processing
Home-page: http://matousc89.github.io/padasip/
Download-URL: https://github.com/matousc89/padasip/
Author: Matous Cejnek
Author-email: matousc@gmail.com
Maintainer: Matous Cejnek
License: MIT
Keywords: signal-processing,adaptive filters
Platform: UNKNOWN
Classifier: Development Status :: 3 - Alpha
Classifier: License :: OSI Approved :: MIT License
Classifier: Topic :: Adaptive Technologies
Classifier: Topic :: Scientific/Engineering :: Artificial Intelligence
Classifier: Topic :: Software Development
Classifier: Intended Audience :: Science/Research
Classifier: Intended Audience :: Developers
Classifier: Intended Audience :: Education
Classifier: Programming Language :: Python
License-File: LICENSE.txt
Requires-Dist: numpy
